[
  {
    "Departamento": "BOACO",
    "Menu": 11
  },
  {
    "Departamento": "CARAZO",
    "Menu": 844
  },
  {
    "Departamento": "CHINANDEGA",
    "Menu": 781
  },
  {
    "Departamento": "CHONTALES",
    "Menu": 6
  },
  {
    "Departamento": "ESTELI                                            ",
    "Menu": 830
  },
  {
    "Departamento": "GRANADA",
    "Menu": 844
  },
  {
    "Departamento": "JINOTEGA",
    "Menu": 435
  },
  {
    "Departamento": "LEON",
    "Menu": 1158
  },
  {
    "Departamento": "MADRIZ",
    "Menu": 218
  },
  {
    "Departamento": "MANAGUA",
    "Menu": 33877
  },
  {
    "Departamento": "MASAYA",
    "Menu": 1632
  },
  {
    "Departamento": "MATAGALPA",
    "Menu": 1651
  },
  {
    "Departamento": "NUEVA SEGOVIA",
    "Menu": 466
  },
  {
    "Departamento": "RAAN                                              ",
    "Menu": 1669
  },
  {
    "Departamento": "RAAS",
    "Menu": 655
  },
  {
    "Departamento": "RIO SAN JUAN",
    "Menu": 762
  },
  {
    "Departamento": "RIVAS",
    "Menu": 550
  }
]